{
  "slug": "haptic-sky",
  "title": "Haptic Sky",
  "year": 2022,
  "type": "설치",
  "tags": [
    "인터랙티브"
  ],
  "tech": [
    "Arduino",
    "Unreal"
  ],
  "production": "개인",
  "thumbnail": "https://picsum.photos/seed/haptic-sky/600/750",
  "grid_type_label": "설치, 인터랙티브",
  "index_type_label": "설치, 인터랙티브, 프로젝션",
  "preview_bg": "https://picsum.photos/seed/haptic-sky/600/750",
  "hero_image": "https://picsum.photos/seed/haptic-sky/600/750",
  "description": "<p>하늘의 빛 변화를 촉각적 경험으로 변환하는 멀티센서리 설치입니다.</p>",
  "meta_year": "2022",
  "meta_type": "인터랙티브 설치",
  "meta_medium": "햅틱 피드백, 프로젝션",
  "meta_tech": "Arduino, Unreal Engine",
  "meta_production": "개인 제작",
  "gallery": [
    "https://picsum.photos/seed/hapticsk1/1920/1440",
    "https://picsum.photos/seed/hapticsk2/1920/1440",
    "https://picsum.photos/seed/hapticsk3/1920/1440"
  ]
}
